[
  {
    "surahNumber": 1,
    "surahName": "Anahtar (El-Fatiha)",
    "totalAyahs": 7,
    "startsWithBasmala": false,
    "startsWithHurufMuqattaat": false
  },
  {
    "surahNumber": 2,
    "surahName": "Düve (El-Bakara)",
    "totalAyahs": 286,
    "startsWithBasmala": true,
    "startsWithHurufMuqattaat": true
  },
  {
    "surahNumber": 3,
    "surahName": "İmran Ailesi (Al-i İmran)",
    "totalAyahs": 200,
    "startsWithBasmala": true,
    "startsWithHurufMuqattaat": true
  },
  {
    "surahNumber": 4,
    "surahName": "Kadınlar (El-Nisa)",
    "totalAyahs": 176,
    "startsWithBasmala": true,
    "startsWithHurufMuqattaat": false
  },
  {
    "surahNumber": 5,
    "surahName": "Ziyafet (El-Ma’ide)",
    "totalAyahs": 120,
    "startsWithBasmala": true,
    "startsWithHurufMuqattaat": false
  },
  {
    "surahNumber": 6,
    "surahName": "Çiftlik Hayvanları (El-En’am)",
    "totalAyahs": 165,
    "startsWithBasmala": true,
    "startsWithHurufMuqattaat": false
  },
  {
    "surahNumber": 7,
    "surahName": "Araf (El-A’raf)",
    "totalAyahs": 206,
    "startsWithBasmala": true,
    "startsWithHurufMuqattaat": true
  },
  {
    "surahNumber": 8,
    "surahName": "Savaş Ganimetleri (El-Enfal)",
    "totalAyahs": 75,
    "startsWithBasmala": true,
    "startsWithHurufMuqattaat": false
  },
  {
    "surahNumber": 9,
    "surahName": "Ültimatom (Berâe)",
    "totalAyahs": 127,
    "startsWithBasmala": false,
    "startsWithHurufMuqattaat": false
  },
  {
    "surahNumber": 10,
    "surahName": "Yunus (Yunus)",
    "totalAyahs": 109,
    "startsWithBasmala": true,
    "startsWithHurufMuqattaat": true
  },
  {
    "surahNumber": 11,
    "surahName": "Hûd (Hûd)",
    "totalAyahs": 123,
    "startsWithBasmala": true,
    "startsWithHurufMuqattaat": true
  },
  {
    "surahNumber": 12,
    "surahName": "Yusuf (Yusuf)",
    "totalAyahs": 111,
    "startsWithBasmala": true,
    "startsWithHurufMuqattaat": true
  },
  {
    "surahNumber": 13,
    "surahName": "Gök Gürlemesi (El-Ra’ad)",
    "totalAyahs": 43,
    "startsWithBasmala": true,
    "startsWithHurufMuqattaat": true
  },
  {
    "surahNumber": 14,
    "surahName": "İbrahim (İbrahîm)",
    "totalAyahs": 52,
    "startsWithBasmala": true,
    "startsWithHurufMuqattaat": true
  },
  {
    "surahNumber": 15,
    "surahName": "Hicr Vadisi (El-Hicr)",
    "totalAyahs": 99,
    "startsWithBasmala": true,
    "startsWithHurufMuqattaat": true
  },
  {
    "surahNumber": 16,
    "surahName": "Arı (El-Nahl)",
    "totalAyahs": 128,
    "startsWithBasmala": true,
    "startsWithHurufMuqattaat": false
  },
  {
    "surahNumber": 17,
    "surahName": "İsrailoğulları (Benî İsrail)",
    "totalAyahs": 111,
    "startsWithBasmala": true,
    "startsWithHurufMuqattaat": false
  },
  {
    "surahNumber": 18,
    "surahName": "Mağara (El-Kehf)",
    "totalAyahs": 110,
    "startsWithBasmala": true,
    "startsWithHurufMuqattaat": false
  },
  {
    "surahNumber": 19,
    "surahName": "Meryem (Meryem)",
    "totalAyahs": 98,
    "startsWithBasmala": true,
    "startsWithHurufMuqattaat": true
  },
  {
    "surahNumber": 20,
    "surahName": "T. H. (Tã Hã)",
    "totalAyahs": 135,
    "startsWithBasmala": true,
    "startsWithHurufMuqattaat": true
  },

  {
    "surahNumber": 21,
    "surahName": "Peygamberler (El-Enbiya)",
    "totalAyahs": 112,
    "startsWithBasmala": true,
    "startsWithHurufMuqattaat": false
  },
  {
    "surahNumber": 22,
    "surahName": "Kutsal Yolculuk (El-Hac)",
    "totalAyahs": 78,
    "startsWithBasmala": true,
    "startsWithHurufMuqattaat": false
  },
  {
    "surahNumber": 23,
    "surahName": "İmanlılar (El-Muminun)",
    "totalAyahs": 118,
    "startsWithBasmala": true,
    "startsWithHurufMuqattaat": false
  },
  {
    "surahNumber": 24,
    "surahName": "Işık (El-Nur)",
    "totalAyahs": 64,
    "startsWithBasmala": true,
    "startsWithHurufMuqattaat": false
  },
  {
    "surahNumber": 25,
    "surahName": "Yasa Kitabı (El-Furkan)",
    "totalAyahs": 77,
    "startsWithBasmala": true,
    "startsWithHurufMuqattaat": false
  },
  {
    "surahNumber": 26,
    "surahName": "Şairler (El-Şu‘arã’)",
    "totalAyahs": 227,
    "startsWithBasmala": true,
    "startsWithHurufMuqattaat": true
  },
  {
    "surahNumber": 27,
    "surahName": "Karınca (El-Neml)",
    "totalAyahs": 93,
    "startsWithBasmala": true,
    "startsWithHurufMuqattaat": true
  },
  {
    "surahNumber": 28,
    "surahName": "Tarih (El-Kasas)",
    "totalAyahs": 88,
    "startsWithBasmala": true,
    "startsWithHurufMuqattaat": true
  },
  {
    "surahNumber": 29,
    "surahName": "Örümcek (El-Ankebut)",
    "totalAyahs": 69,
    "startsWithBasmala": true,
    "startsWithHurufMuqattaat": true
  },
  {
    "surahNumber": 30,
    "surahName": "Romalılar (El-Rum)",
    "totalAyahs": 60,
    "startsWithBasmala": true,
    "startsWithHurufMuqattaat": true
  },
  {
    "surahNumber": 31,
    "surahName": "Lokman (Lokman)",
    "totalAyahs": 34,
    "startsWithBasmala": true,
    "startsWithHurufMuqattaat": true
  },
  {
    "surahNumber": 32,
    "surahName": "Secde (El-Secde)",
    "totalAyahs": 30,
    "startsWithBasmala": true,
    "startsWithHurufMuqattaat": true
  },
  {
    "surahNumber": 33,
    "surahName": "Taraflar (El-Ahzâb)",
    "totalAyahs": 73,
    "startsWithBasmala": true,
    "startsWithHurufMuqattaat": false
  },
  {
    "surahNumber": 34,
    "surahName": "Saba (Saba’)",
    "totalAyahs": 54,
    "startsWithBasmala": true,
    "startsWithHurufMuqattaat": false
  },
  {
    "surahNumber": 35,
    "surahName": "Başlatan (Fãtır)",
    "totalAyahs": 45,
    "startsWithBasmala": true,
    "startsWithHurufMuqattaat": false
  },
  {
    "surahNumber": 36,
    "surahName": "Y. S. (Ya Sîn)",
    "totalAyahs": 83,
    "startsWithBasmala": true,
    "startsWithHurufMuqattaat": true
  },
  {
    "surahNumber": 37,
    "surahName": "Düzenleyenler (El-Saffat)",
    "totalAyahs": 182,
    "startsWithBasmala": true,
    "startsWithHurufMuqattaat": false
  },
  {
    "surahNumber": 38,
    "surahName": "S (Saad)",
    "totalAyahs": 88,
    "startsWithBasmala": true,
    "startsWithHurufMuqattaat": true
  },
  {
    "surahNumber": 39,
    "surahName": "Yığınlar (El-Zümer)",
    "totalAyahs": 75,
    "startsWithBasmala": true,
    "startsWithHurufMuqattaat": false
  },
  {
    "surahNumber": 40,
    "surahName": "Bağışlayıcı (Ğafir)",
    "totalAyahs": 85,
    "startsWithBasmala": true,
    "startsWithHurufMuqattaat": true
  },

  {
    "surahNumber": 41,
    "surahName": "Detaylandırılmış (Fussilet)",
    "totalAyahs": 54,
    "startsWithBasmala": true,
    "startsWithHurufMuqattaat": true
  },
  {
    "surahNumber": 42,
    "surahName": "İstişare (El-Şura)",
    "totalAyahs": 53,
    "startsWithBasmala": true,
    "startsWithHurufMuqattaat": true
  },
  {
    "surahNumber": 43,
    "surahName": "Süsler (El-Zuhruf)",
    "totalAyahs": 89,
    "startsWithBasmala": true,
    "startsWithHurufMuqattaat": true
  },
  {
    "surahNumber": 44,
    "surahName": "Duman (El-Duhan)",
    "totalAyahs": 59,
    "startsWithBasmala": true,
    "startsWithHurufMuqattaat": true
  },
  {
    "surahNumber": 45,
    "surahName": "Diz Çöküş (El-Casiye)",
    "totalAyahs": 37,
    "startsWithBasmala": true,
    "startsWithHurufMuqattaat": true
  },
  {
    "surahNumber": 46,
    "surahName": "Kum Tepeleri (El-Ahkâf)",
    "totalAyahs": 35,
    "startsWithBasmala": true,
    "startsWithHurufMuqattaat": true
  },
  {
    "surahNumber": 47,
    "surahName": "Muhammed",
    "totalAyahs": 38,
    "startsWithBasmala": true,
    "startsWithHurufMuqattaat": false
  },
  {
    "surahNumber": 48,
    "surahName": "Galibiyet (El-Fetih)",
    "totalAyahs": 29,
    "startsWithBasmala": true,
    "startsWithHurufMuqattaat": false
  },
  {
    "surahNumber": 49,
    "surahName": "Duvarlar (El-Hucurat)",
    "totalAyahs": 18,
    "startsWithBasmala": true,
    "startsWithHurufMuqattaat": false
  },
  {
    "surahNumber": 50,
    "surahName": "Q (Qaf)",
    "totalAyahs": 45,
    "startsWithBasmala": true,
    "startsWithHurufMuqattaat": true
  },
  {
    "surahNumber": 51,
    "surahName": "Rüzgârları Sürükleyenler (El-Zariyat)",
    "totalAyahs": 60,
    "startsWithBasmala": true,
    "startsWithHurufMuqattaat": false
  },
  {
    "surahNumber": 52,
    "surahName": "Sina Dağı (El-Tur)",
    "totalAyahs": 49,
    "startsWithBasmala": true,
    "startsWithHurufMuqattaat": false
  },
  {
    "surahNumber": 53,
    "surahName": "Yıldızlar (El-Necm)",
    "totalAyahs": 62,
    "startsWithBasmala": true,
    "startsWithHurufMuqattaat": false
  },
  {
    "surahNumber": 54,
    "surahName": "Ay (El-Kamer)",
    "totalAyahs": 55,
    "startsWithBasmala": true,
    "startsWithHurufMuqattaat": false
  },
  {
    "surahNumber": 55,
    "surahName": "En Lütufkâr Olan (El-Rahman)",
    "totalAyahs": 78,
    "startsWithBasmala": true,
    "startsWithHurufMuqattaat": false
  },
  {
    "surahNumber": 56,
    "surahName": "Kaçınılmaz Olan (El-Vakıa)",
    "totalAyahs": 96,
    "startsWithBasmala": true,
    "startsWithHurufMuqattaat": false
  },
  {
    "surahNumber": 57,
    "surahName": "Demir (El-Hadid)",
    "totalAyahs": 29,
    "startsWithBasmala": true,
    "startsWithHurufMuqattaat": false
  },
  {
    "surahNumber": 58,
    "surahName": "Tartışma (El-Mücadele)",
    "totalAyahs": 22,
    "startsWithBasmala": true,
    "startsWithHurufMuqattaat": false
  },
  {
    "surahNumber": 59,
    "surahName": "Çıkış (El-Haşr)",
    "totalAyahs": 24,
    "startsWithBasmala": true,
    "startsWithHurufMuqattaat": false
  },
  {
    "surahNumber": 60,
    "surahName": "Test (El-Mumtahine)",
    "totalAyahs": 13,
    "startsWithBasmala": true,
    "startsWithHurufMuqattaat": false
  },

  {
    "surahNumber": 61,
    "surahName": "Sütun (El-Saff)",
    "totalAyahs": 14,
    "startsWithBasmala": true,
    "startsWithHurufMuqattaat": false
  },
  {
    "surahNumber": 62,
    "surahName": "Cuma (El-Cum’a)",
    "totalAyahs": 11,
    "startsWithBasmala": true,
    "startsWithHurufMuqattaat": false
  },
  {
    "surahNumber": 63,
    "surahName": "İkiyüzlüler (El-Münafikun)",
    "totalAyahs": 11,
    "startsWithBasmala": true,
    "startsWithHurufMuqattaat": false
  },
  {
    "surahNumber": 64,
    "surahName": "Karşılıklı Suçlama (El-Teğabun)",
    "totalAyahs": 18,
    "startsWithBasmala": true,
    "startsWithHurufMuqattaat": false
  },
  {
    "surahNumber": 65,
    "surahName": "Boşanma (El-Talak)",
    "totalAyahs": 12,
    "startsWithBasmala": true,
    "startsWithHurufMuqattaat": false
  },
  {
    "surahNumber": 66,
    "surahName": "Haram Kılmak (El-Tahrim)",
    "totalAyahs": 12,
    "startsWithBasmala": true,
    "startsWithHurufMuqattaat": false
  },
  {
    "surahNumber": 67,
    "surahName": "Saltanat (El-Mülk)",
    "totalAyahs": 30,
    "startsWithBasmala": true,
    "startsWithHurufMuqattaat": false
  },
  {
    "surahNumber": 68,
    "surahName": "Kalem (El-Kalem)",
    "totalAyahs": 52,
    "startsWithBasmala": true,
    "startsWithHurufMuqattaat": true
  },
  {
    "surahNumber": 69,
    "surahName": "Tartışmasız (El-Hakka)",
    "totalAyahs": 52,
    "startsWithBasmala": true,
    "startsWithHurufMuqattaat": false
  },
  {
    "surahNumber": 70,
    "surahName": "Zirveler (El-Mearic)",
    "totalAyahs": 44,
    "startsWithBasmala": true,
    "startsWithHurufMuqattaat": false
  },
  {
    "surahNumber": 71,
    "surahName": "Nuh",
    "totalAyahs": 28,
    "startsWithBasmala": true,
    "startsWithHurufMuqattaat": false
  },
  {
    "surahNumber": 72,
    "surahName": "Cinler (El-Cin)",
    "totalAyahs": 28,
    "startsWithBasmala": true,
    "startsWithHurufMuqattaat": false
  },
  {
    "surahNumber": 73,
    "surahName": "Örtülmüş (El-Müzzemmil)",
    "totalAyahs": 20,
    "startsWithBasmala": true,
    "startsWithHurufMuqattaat": false
  },
  {
    "surahNumber": 74,
    "surahName": "Gizlenmiş Sır (El-Müddessir)",
    "totalAyahs": 56,
    "startsWithBasmala": true,
    "startsWithHurufMuqattaat": false
  },
  {
    "surahNumber": 75,
    "surahName": "Diriliş (El-Kıyame)",
    "totalAyahs": 40,
    "startsWithBasmala": true,
    "startsWithHurufMuqattaat": false
  },
  {
    "surahNumber": 76,
    "surahName": "İnsan (El-İnsan)",
    "totalAyahs": 31,
    "startsWithBasmala": true,
    "startsWithHurufMuqattaat": false
  },
  {
    "surahNumber": 77,
    "surahName": "Sevk Edilen (El-Murselat)",
    "totalAyahs": 50,
    "startsWithBasmala": true,
    "startsWithHurufMuqattaat": false
  },
  {
    "surahNumber": 78,
    "surahName": "Olay (El-Nebe)",
    "totalAyahs": 40,
    "startsWithBasmala": true,
    "startsWithHurufMuqattaat": false
  },
  {
    "surahNumber": 79,
    "surahName": "Koparanlar (El-Naziat)",
    "totalAyahs": 46,
    "startsWithBasmala": true,
    "startsWithHurufMuqattaat": false
  },
  {
    "surahNumber": 80,
    "surahName": "Surat Astı (Abese)",
    "totalAyahs": 42,
    "startsWithBasmala": true,
    "startsWithHurufMuqattaat": false
  },

  {
    "surahNumber": 81,
    "surahName": "Yuvarlanma (El-Tekvir)",
    "totalAyahs": 29,
    "startsWithBasmala": true,
    "startsWithHurufMuqattaat": false
  },
  {
    "surahNumber": 82,
    "surahName": "Parçalara Ayrılma (El-İnfitar)",
    "totalAyahs": 19,
    "startsWithBasmala": true,
    "startsWithHurufMuqattaat": false
  },
  {
    "surahNumber": 83,
    "surahName": "Hile Yapanlar (El-Mutaffifin)",
    "totalAyahs": 36,
    "startsWithBasmala": true,
    "startsWithHurufMuqattaat": false
  },
  {
    "surahNumber": 84,
    "surahName": "Yarılma (El-İnşikak)",
    "totalAyahs": 25,
    "startsWithBasmala": true,
    "startsWithHurufMuqattaat": false
  },
  {
    "surahNumber": 85,
    "surahName": "Galaksiler (El-Buruc)",
    "totalAyahs": 22,
    "startsWithBasmala": true,
    "startsWithHurufMuqattaat": false
  },
  {
    "surahNumber": 86,
    "surahName": "Parlak Yıldız (El-Tarık)",
    "totalAyahs": 17,
    "startsWithBasmala": true,
    "startsWithHurufMuqattaat": false
  },
  {
    "surahNumber": 87,
    "surahName": "Yüceler Yücesi (El-A’la)",
    "totalAyahs": 19,
    "startsWithBasmala": true,
    "startsWithHurufMuqattaat": false
  },
  {
    "surahNumber": 88,
    "surahName": "Bunaltıcı (El-Ğaşiye)",
    "totalAyahs": 26,
    "startsWithBasmala": true,
    "startsWithHurufMuqattaat": false
  },
  {
    "surahNumber": 89,
    "surahName": "Şafak (El-Fecr)",
    "totalAyahs": 30,
    "startsWithBasmala": true,
    "startsWithHurufMuqattaat": false
  },
  {
    "surahNumber": 90,
    "surahName": "Kent (El-Beled)",
    "totalAyahs": 20,
    "startsWithBasmala": true,
    "startsWithHurufMuqattaat": false
  },
  {
    "surahNumber": 91,
    "surahName": "Güneş (El-Şems)",
    "totalAyahs": 15,
    "startsWithBasmala": true,
    "startsWithHurufMuqattaat": false
  },
  {
    "surahNumber": 92,
    "surahName": "Gece (El-Leyl)",
    "totalAyahs": 21,
    "startsWithBasmala": true,
    "startsWithHurufMuqattaat": false
  },
  {
    "surahNumber": 93,
    "surahName": "Kuşluk Vakti (El-Duha)",
    "totalAyahs": 11,
    "startsWithBasmala": true,
    "startsWithHurufMuqattaat": false
  },
  {
    "surahNumber": 94,
    "surahName": "Öfkeyi Yatıştırmak (El-Şarh)",
    "totalAyahs": 8,
    "startsWithBasmala": true,
    "startsWithHurufMuqattaat": false
  },
  {
    "surahNumber": 95,
    "surahName": "İncir (El-Tin)",
    "totalAyahs": 8,
    "startsWithBasmala": true,
    "startsWithHurufMuqattaat": false
  },
  {
    "surahNumber": 96,
    "surahName": "Embriyo (El-Alak)",
    "totalAyahs": 19,
    "startsWithBasmala": true,
    "startsWithHurufMuqattaat": false
  },
  {
    "surahNumber": 97,
    "surahName": "Kader (El-Kadr)",
    "totalAyahs": 5,
    "startsWithBasmala": true,
    "startsWithHurufMuqattaat": false
  },
  {
    "surahNumber": 98,
    "surahName": "Kanıt (El-Beyyine)",
    "totalAyahs": 8,
    "startsWithBasmala": true,
    "startsWithHurufMuqattaat": false
  },
  {
    "surahNumber": 99,
    "surahName": "Sarsıntı (El-Zilzal)",
    "totalAyahs": 8,
    "startsWithBasmala": true,
    "startsWithHurufMuqattaat": false
  },
  {
    "surahNumber": 100,
    "surahName": "Dört Nala Koşanlar (El-Adiyat)",
    "totalAyahs": 11,
    "startsWithBasmala": true,
    "startsWithHurufMuqattaat": false
  },

  {
    "surahNumber": 101,
    "surahName": "Şok Edici (El-Karia)",
    "totalAyahs": 11,
    "startsWithBasmala": true,
    "startsWithHurufMuqattaat": false
  },
  {
    "surahNumber": 102,
    "surahName": "İstiflemek (El-Tekasür)",
    "totalAyahs": 8,
    "startsWithBasmala": true,
    "startsWithHurufMuqattaat": false
  },
  {
    "surahNumber": 103,
    "surahName": "İkindi (El-Asr)",
    "totalAyahs": 3,
    "startsWithBasmala": true,
    "startsWithHurufMuqattaat": false
  },
  {
    "surahNumber": 104,
    "surahName": "Dedikoducu (El-Hümeze)",
    "totalAyahs": 9,
    "startsWithBasmala": true,
    "startsWithHurufMuqattaat": false
  },
  {
    "surahNumber": 105,
    "surahName": "Fil (El-Fil)",
    "totalAyahs": 5,
    "startsWithBasmala": true,
    "startsWithHurufMuqattaat": false
  },
  {
    "surahNumber": 106,
    "surahName": "Kureyş Kabilesi (Kureyş)",
    "totalAyahs": 4,
    "startsWithBasmala": true,
    "startsWithHurufMuqattaat": false
  },
  {
    "surahNumber": 107,
    "surahName": "Hayır İşi (El-Maun)",
    "totalAyahs": 7,
    "startsWithBasmala": true,
    "startsWithHurufMuqattaat": false
  },
  {
    "surahNumber": 108,
    "surahName": "Cömertçe Verilmiş Nimet (El-Kevser)",
    "totalAyahs": 3,
    "startsWithBasmala": true,
    "startsWithHurufMuqattaat": false
  },
  {
    "surahNumber": 109,
    "surahName": "İnkârcılar (El-Kafirun)",
    "totalAyahs": 6,
    "startsWithBasmala": true,
    "startsWithHurufMuqattaat": false
  },
  {
    "surahNumber": 110,
    "surahName": "Zafer (El-Nasr)",
    "totalAyahs": 3,
    "startsWithBasmala": true,
    "startsWithHurufMuqattaat": false
  },
  {
    "surahNumber": 111,
    "surahName": "Dikenler (El-Mesed)",
    "totalAyahs": 5,
    "startsWithBasmala": true,
    "startsWithHurufMuqattaat": false
  },
  {
    "surahNumber": 112,
    "surahName": "Mutlaklık (El-İhlas)",
    "totalAyahs": 4,
    "startsWithBasmala": true,
    "startsWithHurufMuqattaat": false
  },
  {
    "surahNumber": 113,
    "surahName": "Tan Vakti (El-Felak)",
    "totalAyahs": 5,
    "startsWithBasmala": true,
    "startsWithHurufMuqattaat": false
  },
  {
    "surahNumber": 114,
    "surahName": "İnsanlar (El-Nas)",
    "totalAyahs": 6,
    "startsWithBasmala": true,
    "startsWithHurufMuqattaat": false
  }
  
]
